__init__.py
Common/__init__.py
Common/utility.py
Parser/__init__.py
Parser/base_parser.py
Parser/books_parser.py
Parser/caves_parser.py
Parser/cite_parser.py
Parser/eslite_parser.py
Parser/kingstone_parser.py
Parser/linking_parser.py
Parser/momo_parser.py
Parser/parser_factory.py
Parser/pchome_parser.py
Parser/rakuten_parser.py
Parser/sanmin_parser.py
Parser/taaze_parser.py
Parser/tcsb_parser.py
Parser/tenlong_parser.py
Parser/udn_parser.py
Parser/yahoo_parser.py
pickbooks_lib_scraper-0.0.2.dist-info/METADATA
pickbooks_lib_scraper-0.0.2.dist-info/WHEEL
pickbooks_lib_scraper-0.0.2.dist-info/RECORD
