Metadata-Version: 2.1
Name: pickbooks_lib_scraper
Version: 0.0.2
Summary: A small example package
Project-URL: Homepage, https://github.com/StevenCafe/pickbooks_lib_scraper
Project-URL: Bug Tracker, https://github.com/StevenCafe/pickbooks_lib_scraper/issues
Author-email: StevenCafe <pinylnln@google.com>
Classifier: License :: OSI Approved :: MIT License
Classifier: Operating System :: OS Independent
Classifier: Programming Language :: Python :: 3
Requires-Python: >=3.8.10
